rm_pycache.py
rm_pycache-1.0.2.dist-info/LICENSE
rm_pycache-1.0.2.dist-info/METADATA
rm_pycache-1.0.2.dist-info/WHEEL
rm_pycache-1.0.2.dist-info/RECORD
